{"\n": 0, "S": 1, "O": 2, "C": 3, ".": 4, " ": 5, "I": 6, "n": 7, "A": 8, "t": 9, "h": 10, "e": 11, "s": 12, ",": 13, "E": 14, "u": 15, "y": 16, "p": 17, "r": 18, "o": 19, "i": 20, "c": 21, "a": 22, "l": 23, "d": 24, "b": 25, "m": 26, "U": 27, "T": 28, "H": 29, "R": 30, "?": 31, "v": 32, "F": 33, "w": 34, "f": 35, "g": 36, "B": 37, "Y": 38, "W": 39, "k": 40, "M": 41, "P": 42, "N": 43, "z": 44, "j": 45, "x": 46, "-": 47, ":": 48, "!": 49, "q": 50, "V": 51, "Z": 52, "\"": 53, "'": 54, ";": 55, "G": 56, "D": 57, "L": 58, "(": 59, ")": 60, "Q": 61, "K": 62, "1": 63, "9": 64, "8": 65, "6": 66}